FlyMoon/__init__.py
FlyMoon/agent_client.py
FlyMoon/client.py
FlyMoon/environment.py
FlyMoon/server.py
flymoon-0.1.2.dist-info/licenses/LICENSE
flymoon-0.1.2.dist-info/METADATA
flymoon-0.1.2.dist-info/WHEEL
flymoon-0.1.2.dist-info/top_level.txt
flymoon-0.1.2.dist-info/RECORD
