Metadata-Version: 2.4
Name: FlyMoon
Version: 0.1.2
Summary: FlyMoon Python Package for MCP (Mission Control Protocol) clients and server
Author-email: Tanishq <avasterinbloom@gmail.com>
License: MIT
Project-URL: Homepage, https://github.com/tanishqpy/flymoon
Project-URL: Bug Tracker, https://github.com/tanishqpy/flymoon/issues
Classifier: Programming Language :: Python :: 3
Classifier: License :: OSI Approved :: MIT License
Classifier: Operating System :: OS Independent
Requires-Python: >=3.7
License-File: LICENSE
Requires-Dist: requests>=2.25.0
Requires-Dist: fastapi>=0.68.0
Requires-Dist: uvicorn>=0.15.0
Requires-Dist: pydantic>=1.8.2
Dynamic: license-file
